txaioetcd/__init__.py
txaioetcd/_client_aio.py
txaioetcd/_client_commons.py
txaioetcd/_client_pg.py
txaioetcd/_client_tx.py
txaioetcd/_database.py
txaioetcd/_lease.py
txaioetcd/_pmap.py
txaioetcd/_types.py
txaioetcd/_version.py
txaioetcd/cli/__init__.py
txaioetcd/cli/exporter.py
txaioetcd/cli/importer.py
txaioetcd-18.10.2.data/data/LICENSE
txaioetcd-18.10.2.dist-info/LICENSE
txaioetcd-18.10.2.dist-info/METADATA
txaioetcd-18.10.2.dist-info/WHEEL
txaioetcd-18.10.2.dist-info/entry_points.txt
txaioetcd-18.10.2.dist-info/top_level.txt
txaioetcd-18.10.2.dist-info/zip-safe
txaioetcd-18.10.2.dist-info/RECORD
