Metadata-Version: 2.1
Name: txaioetcd
Version: 18.10.2
Summary: Asynchronous client library for etcd3
Home-page: https://github.com/crossbario/txaio-etcd
Author: Crossbar.io Technologies GmbH
Author-email: autobahnws@googlegroups.com
License: MIT License
Keywords: twisted etcd etcd3
Platform: Any
Classifier: License :: OSI Approved :: MIT License
Classifier: Development Status :: 4 - Beta
Classifier: Environment :: Console
Classifier: Framework :: Twisted
Classifier: Intended Audience :: Developers
Classifier: Operating System :: OS Independent
Classifier: Programming Language :: Python
Classifier: Programming Language :: Python :: 2
Classifier: Programming Language :: Python :: 2.7
Classifier: Programming Language :: Python :: 3
Classifier: Programming Language :: Python :: 3.4
Classifier: Programming Language :: Python :: 3.5
Classifier: Programming Language :: Python :: 3.6
Classifier: Programming Language :: Python :: 3.7
Classifier: Programming Language :: Python :: Implementation :: CPython
Classifier: Programming Language :: Python :: Implementation :: PyPy
Classifier: Topic :: Software Development :: Libraries
Requires-Dist: six (>=1.10.0)
Requires-Dist: txaio (>=2.6.1)
Requires-Dist: twisted (>=16.6.0)
Requires-Dist: treq (>=16.12.0)
Requires-Dist: zlmdb (>=18.10.1)
Requires-Dist: aiohttp (>=2.2.5); python_version >= '3.4'
Provides-Extra: dev
Requires-Dist: pip (>=9.0.1); extra == 'dev'
Requires-Dist: bumpversion (>=0.5.3); extra == 'dev'
Requires-Dist: wheel (>=0.30.0); extra == 'dev'
Requires-Dist: watchdog (>=0.8.3); extra == 'dev'
Requires-Dist: flake8 (>=3.5.0); extra == 'dev'
Requires-Dist: tox (>=2.9.1); extra == 'dev'
Requires-Dist: codecov (>=2.0.15); extra == 'dev'
Requires-Dist: sphinx (>=1.7.1); extra == 'dev'
Requires-Dist: twine (>=1.10.0); extra == 'dev'
Requires-Dist: pytest (>=3.4.2); extra == 'dev'
Requires-Dist: pytest-runner (>=2.11.1); extra == 'dev'
Requires-Dist: humanize (>=0.5.1); extra == 'dev'
Requires-Dist: backports.tempfile (>=1.0); extra == 'dev'
Requires-Dist: yapf (>=0.22.0); extra == 'dev'
Requires-Dist: pylint (>=1.9.2); extra == 'dev'
Requires-Dist: mypy (>=0.610); (python_version >= "3.4" and platform_python_implementation != "PyPy") and extra == 'dev'
